noisy_outlier/__init__.py
noisy_outlier/hyperopt/__init__.py
noisy_outlier/hyperopt/hyperopt.py
noisy_outlier/model/__init__.py
noisy_outlier/model/model.py
noisy_outlier/model/transformer.py
noisy_outlier-0.1.6.dist-info/LICENSE
noisy_outlier-0.1.6.dist-info/WHEEL
noisy_outlier-0.1.6.dist-info/METADATA
noisy_outlier-0.1.6.dist-info/RECORD
