Metadata-Version: 2.1
Name: noisy-outlier
Version: 0.1.6
Summary: Self-Supervised Learning for Outlier Detection
Home-page: https://github.com/jandiers/self-supervised-outlier
Author: JanDiers
Author-email: jan.diers@uni-jena.de
Requires-Python: >=3.8,<4.0
Classifier: Programming Language :: Python :: 3
Classifier: Programming Language :: Python :: 3.10
Classifier: Programming Language :: Python :: 3.8
Classifier: Programming Language :: Python :: 3.9
Requires-Dist: numpy (>=1.24.3,<2.0.0)
Requires-Dist: scikit-learn (>=1.2.2,<2.0.0)
Project-URL: Documentation, https://github.com/jandiers/self-supervised-outlier
